allset
