Metadata-Version: 1.1
Name: allset
Version: 1.0.1
Summary: Generates dynamic bindings for module imports
Home-page: https://github.com/OpenGov/allset
Author: Matthew Seal
Author-email: mseal@opengov.com
License: New BSD
Download-URL: https://github.com/OpenGov/allset/tarball/v1.0.1
Keywords: importing
Platform: UNKNOWN
Classifier: Development Status :: 4 - Beta
Classifier: Topic :: Utilities
Classifier: License :: OSI Approved :: BSD License
Classifier: Natural Language :: English
Classifier: Programming Language :: Python :: 2 :: Only
